django_auxilium/__init__.py
django_auxilium/callback_mail/__init__.py
django_auxilium/callback_mail/base.py
django_auxilium/callback_mail/filebased.py
django_auxilium/callback_mail/signals.py
django_auxilium/callback_mail/smtp.py
django_auxilium/forms/__init__.py
django_auxilium/forms/color.py
django_auxilium/forms/files.py
django_auxilium/forms/multiple_values.py
django_auxilium/forms/range.py
django_auxilium/middleware/__init__.py
django_auxilium/middleware/html.py
django_auxilium/models/__init__.py
django_auxilium/models/base.py
django_auxilium/models/signals.py
django_auxilium/models/fields/__init__.py
django_auxilium/models/fields/files.py
django_auxilium/utils/__init__.py
django_auxilium/utils/content_type.py
django_auxilium/utils/html.py
django_auxilium/utils/range.py
django_auxilium/utils/string.py
django_auxilium/utils/functools/__init__.py
django_auxilium/utils/functools/cache.py
django_auxilium/utils/functools/decorators.py
django_auxilium/utils/functools/lazy.py
django_auxilium/views/__init__.py
django_auxilium/views/wizard.py
django_auxilium-0.1.4.dist-info/METADATA
django_auxilium-0.1.4.dist-info/RECORD
django_auxilium-0.1.4.dist-info/WHEEL
django_auxilium-0.1.4.dist-info/top_level.txt
test_project/__init__.py
test_project/settings.py
