Metadata-Version: 2.1
Name: django-auxilium
Version: 0.1.4
Summary: Django utility app to help in Django development
Home-page: https://github.com/miki725/django-auxilium
Author: Miroslav Shubernetskiy
Author-email: UNKNOWN
License: MIT
Keywords: django
Platform: UNKNOWN
Classifier: Intended Audience :: Developers
Classifier: Natural Language :: English
Classifier: License :: OSI Approved :: MIT License
Classifier: Programming Language :: Python
Classifier: Programming Language :: Python :: 2
Classifier: Programming Language :: Python :: 3
Classifier: Development Status :: 2 - Pre-Alpha
Requires-Dist: django
Requires-Dist: pathlib
Requires-Dist: six
Requires-Dist: setuptools
